pazlexer/__init__.py
pazlexer/core.py
pazlexer/data/0.txt
pazlexer/data/1.txt
pazlexer/data/2.txt
pazlexer/data/3.txt
pazlexer/data/5.txt
pazlexer/data/6.txt
pazlexer/data/7.txt
pazlexer/data/8.txt
pazlexer-1.1.1.dist-info/METADATA
pazlexer-1.1.1.dist-info/WHEEL
pazlexer-1.1.1.dist-info/top_level.txt
pazlexer-1.1.1.dist-info/RECORD
