Metadata-Version: 2.4
Name: pazlexer
Version: 1.1.1
Summary: A Python package that help student to develop they programming knowlegde 
Author: 73
Author-email: 73@gmail.com
Classifier: Programming Language :: Python :: 3
Classifier: License :: OSI Approved :: MIT License
Classifier: Operating System :: OS Independent
Requires-Python: >=3.6
Dynamic: author
Dynamic: author-email
Dynamic: classifier
Dynamic: requires-python
Dynamic: summary
